{"chunk_definitions":[{"row":18,"row_count":1,"visible":true,"expansion_state":0,"options":{"engine":"r","label":"setup","include":false},"document_id":"B042903F","chunk_id":"csetup_chunk","chunk_label":"setup"},{"row":40,"row_count":1,"visible":true,"expansion_state":0,"options":{"engine":"r","label":"unnamed-chunk-6"},"document_id":"B042903F","chunk_id":"ckht4t87marpg","chunk_label":"unnamed-chunk-1"},{"row":70,"row_count":1,"visible":true,"expansion_state":0,"options":{"engine":"r","label":"unnamed-chunk-7"},"document_id":"B042903F","chunk_id":"c4addf2yq3k19","chunk_label":"unnamed-chunk-2"},{"row":101,"row_count":1,"visible":true,"expansion_state":0,"options":{"engine":"r","label":"unnamed-chunk-8"},"document_id":"B042903F","chunk_id":"c4u6yq6mr2dh4","chunk_label":"unnamed-chunk-3"},{"row":128,"row_count":1,"visible":true,"expansion_state":0,"options":{"engine":"r","label":"unnamed-chunk-9"},"document_id":"B042903F","chunk_id":"cvoe4uxatag4t","chunk_label":"unnamed-chunk-4"},{"row":149,"row_count":1,"visible":true,"expansion_state":0,"options":{"engine":"r","label":"unnamed-chunk-10"},"document_id":"B042903F","chunk_id":"ct4a36aibbfpb","chunk_label":"unnamed-chunk-5"},{"row":171,"row_count":1,"visible":true,"expansion_state":0,"options":{"engine":"r","label":"unnamed-chunk-11"},"document_id":"B042903F","chunk_id":"cxmg6r6lnggfk","chunk_label":"unnamed-chunk-6"},{"row":227,"row_count":1,"visible":true,"expansion_state":0,"options":{"engine":"r","label":"unnamed-chunk-12"},"document_id":"B042903F","chunk_id":"csml4jnvhzaf6","chunk_label":"unnamed-chunk-7"},{"row":256,"row_count":1,"visible":true,"expansion_state":0,"options":{"engine":"r","warning":false,"label":"unnamed-chunk-13"},"document_id":"B042903F","chunk_id":"cxzeojxtl6bas","chunk_label":"unnamed-chunk-8"},{"row":317,"row_count":1,"visible":true,"expansion_state":0,"options":{"engine":"r","label":"unnamed-chunk-14"},"document_id":"B042903F","chunk_id":"cqmzhzagkzqul","chunk_label":"unnamed-chunk-9"},{"row":372,"row_count":1,"visible":true,"expansion_state":0,"options":{"engine":"r","label":"unnamed-chunk-15"},"document_id":"B042903F","chunk_id":"cvsxdaq6mfkko","chunk_label":"unnamed-chunk-10"},{"row":444,"row_count":1,"visible":true,"expansion_state":0,"options":{"engine":"r","label":"unnamed-chunk-16"},"document_id":"B042903F","chunk_id":"c4fsc3v2a46oe","chunk_label":"unnamed-chunk-11"},{"row":464,"row_count":1,"visible":true,"expansion_state":0,"options":{"engine":"r","label":"unnamed-chunk-17"},"document_id":"B042903F","chunk_id":"ctp5xj7rewcc9","chunk_label":"unnamed-chunk-12"},{"row":493,"row_count":1,"visible":true,"expansion_state":0,"options":{"engine":"r","label":"unnamed-chunk-18"},"document_id":"B042903F","chunk_id":"cutqsq7fein42","chunk_label":"unnamed-chunk-13"},{"row":525,"row_count":1,"visible":true,"expansion_state":0,"options":{"engine":"r","label":"unnamed-chunk-19"},"document_id":"B042903F","chunk_id":"c1j3xzk40ufpb","chunk_label":"unnamed-chunk-14"},{"row":553,"row_count":1,"visible":true,"expansion_state":0,"options":{},"document_id":"B042903F","chunk_id":"cmr4e4uvpu9si","chunk_label":"unnamed-chunk-15"},{"row":585,"row_count":1,"visible":true,"expansion_state":0,"options":{},"document_id":"B042903F","chunk_id":"cit6eclho0xol","chunk_label":"unnamed-chunk-16"},{"row":612,"row_count":1,"visible":true,"expansion_state":0,"options":{"engine":"r","label":"unnamed-chunk-48"},"document_id":"7EA87356","chunk_id":"c7akq7r40qzn3","chunk_label":"unnamed-chunk-17"},{"row":714,"row_count":1,"visible":true,"expansion_state":0,"options":{"engine":"r","label":"unnamed-chunk-64"},"document_id":"7EA87356","chunk_id":"c7nosac66nrll","chunk_label":"unnamed-chunk-18"},{"row":733,"row_count":1,"visible":true,"expansion_state":0,"options":{"engine":"r","label":"unnamed-chunk-65"},"document_id":"7EA87356","chunk_id":"ckqr4kf3bi27p","chunk_label":"unnamed-chunk-19"},{"row":745,"row_count":1,"visible":true,"expansion_state":0,"options":{},"document_id":"B042903F","chunk_id":"c5wh7bwwcknrr","chunk_label":"unnamed-chunk-20"}],"doc_write_time":1682286501,"working_dir":null,"default_chunk_options":{"echo":false,"include":false,"warning":false,"cache":true},"chunk_rendered_width":400}